odoo/addons/pos_picking_delayed/README.rst
odoo/addons/pos_picking_delayed/__init__.py
odoo/addons/pos_picking_delayed/__manifest__.py
odoo/addons/pos_picking_delayed/i18n/ca.po
odoo/addons/pos_picking_delayed/i18n/ca_ES.po
odoo/addons/pos_picking_delayed/i18n/es.po
odoo/addons/pos_picking_delayed/i18n/fr.po
odoo/addons/pos_picking_delayed/i18n/pos_picking_delayed.pot
odoo/addons/pos_picking_delayed/models/__init__.py
odoo/addons/pos_picking_delayed/models/pos_config.py
odoo/addons/pos_picking_delayed/models/pos_order.py
odoo/addons/pos_picking_delayed/readme/CONFIGURE.rst
odoo/addons/pos_picking_delayed/readme/CONTRIBUTORS.rst
odoo/addons/pos_picking_delayed/readme/CREDITS.rst
odoo/addons/pos_picking_delayed/readme/DESCRIPTION.rst
odoo/addons/pos_picking_delayed/readme/USAGE.rst
odoo/addons/pos_picking_delayed/static/description/icon.png
odoo/addons/pos_picking_delayed/static/description/index.html
odoo/addons/pos_picking_delayed/static/description/pos_config_form.png
odoo/addons/pos_picking_delayed/static/description/pos_order_tree.png
odoo/addons/pos_picking_delayed/tests/__init__.py
odoo/addons/pos_picking_delayed/tests/test_module.py
odoo/addons/pos_picking_delayed/views/view_pos_config.xml
odoo/addons/pos_picking_delayed/views/view_pos_order.xml
odoo11_addon_pos_picking_delayed-11.0.1.0.1.dist-info/METADATA
odoo11_addon_pos_picking_delayed-11.0.1.0.1.dist-info/WHEEL
odoo11_addon_pos_picking_delayed-11.0.1.0.1.dist-info/top_level.txt
odoo11_addon_pos_picking_delayed-11.0.1.0.1.dist-info/RECORD
